spectroSLEUTH/__init__.py
spectroSLEUTH/sleuth.py
spectroSLEUTH-1.0.0.dist-info/LICENSE
spectroSLEUTH-1.0.0.dist-info/METADATA
spectroSLEUTH-1.0.0.dist-info/WHEEL
spectroSLEUTH-1.0.0.dist-info/top_level.txt
spectroSLEUTH-1.0.0.dist-info/RECORD
