Metadata-Version: 2.1
Name: spectroSLEUTH
Version: 1.0.0
License-File: LICENSE
Requires-Dist: numpy
Requires-Dist: matplotlib
Requires-Dist: pandas
Requires-Dist: astropy
Requires-Dist: scipy
